<?xml version="1.0" encoding="UTF-8"?>
<sdkExtension
	xmlns="http://www.sap.com/bi/zen/sdk"
	id="com.sap.sample.three"
	title="Design Studio SDK Extension Three JS Test"
	version="14.0"
	vendor="SAP">
	<component
		id="Three"
		title="Three"
		icon="res/icon.png"
		handlerType="div"
		propertySheetPath="res/additional_properties_sheet/additional_properties_sheet.html">
		<jsInclude>res/js/three.min.js</jsInclude>
		<jsInclude>res/js/component.js</jsInclude>
		<cssInclude>res/css/component.css</cssInclude>
		<initialization>
			<defaultValue property="WIDTH">100</defaultValue>
			<defaultValue property="HEIGHT">100</defaultValue>
		</initialization>
	</component>
</sdkExtension>